sellgate/__init__.py
sellgate-1.0.0.dist-info/METADATA
sellgate-1.0.0.dist-info/WHEEL
sellgate-1.0.0.dist-info/top_level.txt
sellgate-1.0.0.dist-info/RECORD
