Metadata-Version: 2.1
Name: sellgate
Version: 1.0.0
Summary: A Python SDK for the Sellgate API
Home-page: https://github.com/sellgate/python-sdk
Author: Sellgate
Author-email: support@sellgate.io
Requires-Dist: requests >=2.25.1
